mofiwo/__init__.py
mofiwo/_version.py
mofiwo/config.env
mofiwo/config.py
mofiwo/logger.py
mofiwo/_helper/__init__.py
mofiwo/_helper/connector_helper.py
mofiwo/_helper/rna_handler_helper.py
mofiwo/connector/__init__.py
mofiwo/connector/ensembl.py
mofiwo/connector/meme.py
mofiwo/utility/__init__.py
mofiwo/utility/rna_handler.py
test/__init__.py
test/unit_tests/__init__.py
test/unit_tests/connector/__init__.py
test/unit_tests/connector/ensembl_test.py
mofiwo-0.post0.dev7.dist-info/METADATA
mofiwo-0.post0.dev7.dist-info/WHEEL
mofiwo-0.post0.dev7.dist-info/top_level.txt
mofiwo-0.post0.dev7.dist-info/RECORD
